conn_check/__init__.py
conn_check/amqp0-8.xml
conn_check/check_impl.py
conn_check/checks.py
conn_check/main.py
conn_check/patterns.py
conn_check/version.txt
conn_check/utils/__init__.py
conn_check/utils/convert_fw_rules.py
conn_check/utils/firewall_rules.py
conn_check-1.5.0.dist-info/METADATA
conn_check-1.5.0.dist-info/RECORD
conn_check-1.5.0.dist-info/WHEEL
conn_check-1.5.0.dist-info/entry_points.txt
conn_check-1.5.0.dist-info/top_level.txt
