Metadata-Version: 2.1
Name: conn-check
Version: 1.5.0
Summary: Utility for verifying connectivity between services
Home-page: http://conn-check.org/
Author: James Westby, Wes Mason
Author-email: james.westby@canonical.com, wesley.mason@canonical.com
License: GPL3
Platform: UNKNOWN
Classifier: Topic :: System :: Networking
Classifier: Development Status :: 4 - Beta
Classifier: Programming Language :: Python
Classifier: Intended Audience :: Developers
Classifier: Operating System :: OS Independent
Classifier: Intended Audience :: System Administrators
Classifier: License :: OSI Approved :: GNU General Public License v3 (GPLv3)
Provides-Extra: all
Provides-Extra: amqp
Provides-Extra: mongodb
Provides-Extra: redis
Provides-Extra: postgres
Provides-Extra: fwutil
Requires-Dist: appdirs
Requires-Dist: characteristic (>=14.0)
Requires-Dist: cryptography (>=0.5)
Requires-Dist: ndg-httpsclient
Requires-Dist: packaging
Requires-Dist: pyasn1
Requires-Dist: pyOpenSSL
Requires-Dist: pyparsing
Requires-Dist: service-identity
Requires-Dist: requests
Requires-Dist: Twisted (>=17)
Requires-Dist: txrequests (>=0.9.6)
Requires-Dist: PyYAML
Requires-Dist: future
Provides-Extra: all
Requires-Dist: txAMQP; extra == 'all'
Requires-Dist: txredis; extra == 'all'
Requires-Dist: psycopg2; extra == 'all'
Requires-Dist: txmongo (>=0.5); extra == 'all'
Requires-Dist: netaddr; extra == 'all'
Provides-Extra: amqp
Requires-Dist: txAMQP; extra == 'amqp'
Provides-Extra: fwutil
Requires-Dist: netaddr; extra == 'fwutil'
Provides-Extra: mongodb
Requires-Dist: txmongo (>=0.5); extra == 'mongodb'
Provides-Extra: postgres
Requires-Dist: psycopg2; extra == 'postgres'
Provides-Extra: redis
Requires-Dist: txredis; extra == 'redis'
